AUTHORS
ChangeLog
LICENSE
MANIFEST.in
README.rst
requirements.txt
setup.cfg
setup.py
openstack_interpreter/__init__.py
openstack_interpreter/plugin.py
openstack_interpreter.egg-info/PKG-INFO
openstack_interpreter.egg-info/SOURCES.txt
openstack_interpreter.egg-info/dependency_links.txt
openstack_interpreter.egg-info/entry_points.txt
openstack_interpreter.egg-info/not-zip-safe
openstack_interpreter.egg-info/pbr.json
openstack_interpreter.egg-info/requires.txt
openstack_interpreter.egg-info/top_level.txt
openstack_interpreter/common/__init__.py
openstack_interpreter/common/output.py
openstack_interpreter/common/profile.py
openstack_interpreter/common/prompt.py
openstack_interpreter/v1/__init__.py
openstack_interpreter/v1/clients.py
openstack_interpreter/v1/command.py
openstack_interpreter/v1/interpreter.py
openstack_interpreter/v1/sdk.py